oauth_toolkit_spa/__init__.py
oauth_toolkit_spa/admin.py
oauth_toolkit_spa/apps.py
oauth_toolkit_spa/mixins.py
oauth_toolkit_spa/serializers.py
oauth_toolkit_spa/settings.py
oauth_toolkit_spa/tests.py
oauth_toolkit_spa/urls.py
oauth_toolkit_spa/views.py
oauth_toolkit_spa/migrations/__init__.py
django_oauth_toolkit_spa-1.0.1.dist-info/LICENSE
django_oauth_toolkit_spa-1.0.1.dist-info/METADATA
django_oauth_toolkit_spa-1.0.1.dist-info/WHEEL
django_oauth_toolkit_spa-1.0.1.dist-info/top_level.txt
django_oauth_toolkit_spa-1.0.1.dist-info/RECORD
